taskqueue/__init__.py
taskqueue/apps.py
taskqueue/celery_app.py
taskqueue/cmanager.py
taskqueue/models.py
taskqueue/slack_notifier.py
taskqueue/libs/__init__.py
taskqueue/libs/helper_test.py
taskqueue/migrations/0001_initial.py
taskqueue/migrations/0002_add_channel_to_taskreconstruction.py
taskqueue/migrations/0003_alter_taskreconstruction_id.py
taskqueue/migrations/0004_add_callable_name_meta_to_taskreconstruction.py
taskqueue/migrations/__init__.py
p1_taskqueue-0.1.32.dist-info/METADATA
p1_taskqueue-0.1.32.dist-info/WHEEL
p1_taskqueue-0.1.32.dist-info/top_level.txt
p1_taskqueue-0.1.32.dist-info/RECORD
