Metadata-Version: 2.4
Name: p1-taskqueue
Version: 0.1.32
Summary: A Task Queue Wrapper for Dekoruma Backend
Author-email: Chalvin <engineering@dekoruma.com>
Project-URL: Homepage, https://github.com/Dekoruma/p1-taskqueue
Project-URL: Repository, https://github.com/Dekoruma/p1-taskqueue.git
Project-URL: Issues, https://github.com/Dekoruma/p1-taskqueue/issues
Classifier: Development Status :: 3 - Alpha
Classifier: Intended Audience :: Developers
Classifier: License :: OSI Approved :: MIT License
Classifier: Programming Language :: Python :: 3.11
Classifier: Programming Language :: Python :: 3.12
Requires-Python: >=3.11
Requires-Dist: celery>=5.5.3
Requires-Dist: redis>=6.4.0
Requires-Dist: kombu>=5.5.4
Requires-Dist: django>=4.0.0
Requires-Dist: django-celery-results>=2.6.0
Requires-Dist: django-celery-beat>=2.8.1
Requires-Dist: requests>=2.32.3
Provides-Extra: dev
Requires-Dist: pytest>=7.0.0; extra == "dev"
Requires-Dist: pytest-cov>=4.0.0; extra == "dev"
Requires-Dist: black>=23.0.0; extra == "dev"
Requires-Dist: flake8>=6.0.0; extra == "dev"
Requires-Dist: mypy>=1.0.0; extra == "dev"
Requires-Dist: pre-commit>=3.0.0; extra == "dev"
